merlin/__init__.py
merlin/algorithms/__init__.py
merlin/algorithms/feed_forward.py
merlin/algorithms/feed_forward_legacy.py
merlin/algorithms/kernels.py
merlin/algorithms/layer.py
merlin/algorithms/loss.py
merlin/bridge/__init__.py
merlin/bridge/quantum_bridge.py
merlin/builder/__init__.py
merlin/builder/circuit_builder.py
merlin/core/__init__.py
merlin/core/base.py
merlin/core/circuit.py
merlin/core/components.py
merlin/core/computation_space.py
merlin/core/generators.py
merlin/core/merlin_processor.py
merlin/core/observables.py
merlin/core/photonicbackend.py
merlin/core/process.py
merlin/datasets/__init__.py
merlin/datasets/fashion_mnist.py
merlin/datasets/iris.py
merlin/datasets/k_mnist.py
merlin/datasets/metadata.py
merlin/datasets/mnist_digits.py
merlin/datasets/spiral.py
merlin/datasets/utils.py
merlin/measurement/__init__.py
merlin/measurement/autodiff.py
merlin/measurement/detectors.py
merlin/measurement/mappers.py
merlin/measurement/photon_loss.py
merlin/measurement/process.py
merlin/measurement/strategies.py
merlin/pcvl_pytorch/__init__.py
merlin/pcvl_pytorch/locirc_to_tensor.py
merlin/pcvl_pytorch/slos_torchscript.py
merlin/pcvl_pytorch/utils.py
merlin/utils/__init__.py
merlin/utils/combinadics.py
merlin/utils/dtypes.py
merlin/utils/grouping.py
merlin/utils/torch_codes.py
merlinquantum-0.2.3.dist-info/licenses/LICENSE
merlinquantum-0.2.3.dist-info/METADATA
merlinquantum-0.2.3.dist-info/WHEEL
merlinquantum-0.2.3.dist-info/top_level.txt
merlinquantum-0.2.3.dist-info/RECORD
