Metadata-Version: 2.4
Name: merlinquantum
Version: 0.2.3
Summary: Quantum neural network models using photonic circuits - Preview
Author: MerLin Team
Author-email: MerLin <MerLin@quandela.com>
License-Expression: MIT
Project-URL: homepage, https://merlinquantum.ai
Project-URL: documentation, https://merlinquantum.ai
Project-URL: source, https://github.com/merlinquantum/merlin
Project-URL: issues, https://github.com/merlinquantum/merlin/issues
Classifier: Development Status :: 4 - Beta
Classifier: Intended Audience :: Science/Research
Classifier: Topic :: Scientific/Engineering :: Artificial Intelligence
Classifier: Topic :: Scientific/Engineering :: Physics
Classifier: Programming Language :: Python :: 3
Classifier: Programming Language :: Python :: 3.10
Classifier: Programming Language :: Python :: 3.11
Classifier: Programming Language :: Python :: 3.12
Requires-Python: >=3.10
License-File: LICENSE
Requires-Dist: torch>=2.0.0
Requires-Dist: perceval-quandela>=0.13.1
Requires-Dist: numpy>=2.2.6
Requires-Dist: pandas
Requires-Dist: scikit-learn>=1.7.2
Provides-Extra: dev
Requires-Dist: pytest>=8.0; extra == "dev"
Requires-Dist: pytest-benchmark>=4.0.0; extra == "dev"
Requires-Dist: pytest-cov>=5.0; extra == "dev"
Requires-Dist: ruff>=0.1.0; extra == "dev"
Requires-Dist: mypy>=1.0; extra == "dev"
Provides-Extra: docs
Requires-Dist: sphinx<7.0.0,>=6.2.1; extra == "docs"
Requires-Dist: sphinx-autodoc-typehints>=1.0.0; extra == "docs"
Requires-Dist: sphinxcontrib-bibtex>=2.5.0; extra == "docs"
Requires-Dist: renku-sphinx-theme; extra == "docs"
Requires-Dist: enum-tools[sphinx]; extra == "docs"
Requires-Dist: nbsphinx; extra == "docs"
Requires-Dist: nbformat; extra == "docs"
Requires-Dist: ipython; extra == "docs"
Requires-Dist: ipykernel; extra == "docs"
Requires-Dist: gitpython; extra == "docs"
Requires-Dist: jinja2==3.0.0; extra == "docs"
Requires-Dist: scikit-learn>=1.0.0; extra == "docs"
Provides-Extra: examples
Requires-Dist: matplotlib>=3.5.0; extra == "examples"
Requires-Dist: scikit-learn>=1.0.0; extra == "examples"
Requires-Dist: jupyter>=1.0.0; extra == "examples"
Dynamic: license-file
